{
  "appInfo" : {
    "build" : "251.25776",
    "buildDate" : "2025-08-03T19:00:49.254Z[Etc/UTC]",
    "productCode" : "QDPY",
    "generated" : "2025-08-03T19:07:25.484997797Z",
    "os" : "Linux 6.6.87.2-microsoft-standard-wsl2",
    "runtime" : "JetBrains s.r.o. 21.0.7 21.0.7+9-b895.115"
  },
  "runtimeInfo" : {
    "maxMemory" : 4108320768,
    "numberOfProcessors" : 16,
    "maxNumberOfIndexingThreads" : 16,
    "maxSizeOfFileForIntelliSense" : 2560000,
    "maxSizeOfFileForContentLoading" : 20971520
  },
  "type" : "Scanning",
  "projectIndexingActivityHistory" : {
    "projectName" : "project",
    "times" : {
      "scanningReason" : "changes in: \"Python SDK Python 3.12 /usr/bin/python3\"",
      "scanningType" : "PARTIAL",
      "scanningId" : 2,
      "creatingIteratorsTime" : 0,
      "concurrentHandlingWallTimeWithoutPauses" : 0,
      "concurrentHandlingWallTimeWithPauses" : 0,
      "concurrentHandlingSumOfThreadTimesWithPauses" : 365324952,
      "concurrentIterationAndScannersApplicationSumOfThreadTimesWithPauses" : 16760395,
      "concurrentFileCheckSumOfThreadTimesWithPauses" : 348275761,
      "delayedPushPropertiesStageTime" : 0,
      "indexExtensionsTime" : 45947578,
      "dumbWallTimeWithPauses" : 0,
      "dumbWallTimeWithoutPauses" : 0,
      "updatingStart" : "2025-08-03T19:07:24.55090089Z",
      "updatingEnd" : "2025-08-03T19:07:25.45398219Z",
      "totalWallTimeWithPauses" : 903081300,
      "wallTimeOnPause" : 655774,
      "isCancelled" : false,
      "totalWallTimeWithoutPauses" : 902425526
    },
    "fileCount" : {
      "numberOfFileProviders" : 1,
      "numberOfScannedFiles" : 6969,
      "numberOfFilesIndexedByInfrastructureExtensionsDuringScan" : 0,
      "numberOfFilesScheduledForIndexingAfterScan" : 6782
    },
    "scanningStatistics" : [ {
      "providerName" : "Python SDK Python 3.12 /usr/bin/python3",
      "numberOfScannedFiles" : 6969,
      "numberOfSkippedFiles" : 2,
      "numberOfFilesForIndexing" : 6782,
      "numberOfFilesFullyIndexedByInfrastructureExtensions" : 0,
      "filesFullyIndexedByInfrastructureExtensions" : [ ],
      "statusTime" : 304189622,
      "totalOneThreadTimeWithPauses" : 365324952,
      "iterationAndScannersApplicationTime" : 16760395,
      "filesCheckTime" : 348275761,
      "timeProcessingUpToDateFiles" : 0,
      "timeUpdatingContentLessIndexes" : 3546146,
      "timeIndexingWithoutContentViaInfrastructureExtension" : 45947578,
      "roots" : [ ]
    } ]
  }
}